datapackage_registry/__init__.py
datapackage_registry/compat.py
datapackage_registry/registry.py
datapackage_registry-0.0.2.dist-info/DESCRIPTION.rst
datapackage_registry-0.0.2.dist-info/METADATA
datapackage_registry-0.0.2.dist-info/metadata.json
datapackage_registry-0.0.2.dist-info/RECORD
datapackage_registry-0.0.2.dist-info/top_level.txt
datapackage_registry-0.0.2.dist-info/WHEEL
