Metadata-Version: 2.0
Name: datapackage-registry
Version: 0.0.2
Summary: A Python library for working with a Data Package Registry.
Home-page: https://github.com/okfn/datapackage-registry-py
Author: Open Knowledge Foundation
Author-email: info@okfn.org
License: MIT
Platform: UNKNOWN
Classifier: Development Status :: 4 - Beta
Classifier: Intended Audience :: Developers
Classifier: License :: OSI Approved :: MIT License
Classifier: Operating System :: OS Independent
Classifier: Programming Language :: Python :: 2
Classifier: Programming Language :: Python :: 2.7
Classifier: Programming Language :: Python :: 3
Classifier: Programming Language :: Python :: 3.3
Classifier: Programming Language :: Python :: 3.4
Classifier: Topic :: Software Development :: Libraries :: Python Modules
Classifier: Topic :: Utilities
Requires-Dist: requests (>=2.8.0)
